gg/__init__.py
gg/ext_packages/__init__.py
gg/ext_packages/better_ffmpeg_progress.py
gg/main.py
gg/README.md
gg/resources/js/youtube.js
gg/resources/ppt/模板01.pptx
gg/resources/ppt/模板02.pptx
gg/start_init.py
gg/utils/__init__.py
gg/utils/common.py
gg/utils/gen_k_image.py
gg/utils/srt.py
gg/utils/youtube.py
gg_daigua-0.2.23.dist-info/entry_points.txt
gg_daigua-0.2.23.dist-info/METADATA
gg_daigua-0.2.23.dist-info/WHEEL
gg_daigua-0.2.23.dist-info/RECORD
