Metadata-Version: 2.1
Name: gg_daigua
Version: 0.2.23
Summary: 方便的工具
Author: 邓润庭
Author-email: 1032939141@qq.com
Requires-Python: >=3.12,<4.0
Classifier: Programming Language :: Python :: 3
Classifier: Programming Language :: Python :: 3.12
Classifier: Programming Language :: Python :: 3.13
Requires-Dist: bs4 (>=0.0.2,<0.0.3)
Requires-Dist: ffmpeg-python (>=0.2.0,<0.3.0)
Requires-Dist: imageio (>=2.36.0,<3.0.0)
Requires-Dist: llvmlite (==0.43.0)
Requires-Dist: moviepy (>=1.0.3,<2.0.0)
Requires-Dist: numba (==0.60.0)
Requires-Dist: openai-whisper (>=20240930,<20240931)
Requires-Dist: opencv-python (>=4.10.0.84,<5.0.0.0)
Requires-Dist: psutil (>=6.1.0,<7.0.0)
Requires-Dist: pyexecjs (>=1.5.1,<2.0.0)
Requires-Dist: python-pptx (>=1.0.2,<2.0.0)
Requires-Dist: requests (>=2.32.3,<3.0.0)
Requires-Dist: typer (>=0.13.0,<0.14.0)
Requires-Dist: whisper (>=1.1.10,<2.0.0)
